ofd2png/__init__.py
ofd2png/cli.py
ofd2png/converter.py
ofd2png/utils.py
ofd2png-0.0.5.dist-info/licenses/LICENSE
ofd2png-0.0.5.dist-info/METADATA
ofd2png-0.0.5.dist-info/WHEEL
ofd2png-0.0.5.dist-info/top_level.txt
ofd2png-0.0.5.dist-info/RECORD
