Metadata-Version: 2.4
Name: ofd2png
Version: 0.0.5
Summary: A package for converting OFD files to PNG format.
Author: cchmkj
Author-email: cchmkj_lzc <cchmkj@163.com>
License: MIT
License-File: LICENSE
Dynamic: license-file
